natural_time/__init__.py
natural_time/dates.py
natural_time/natural_time.py
natural_time/natural_time_parser.py
natural_time/num_parse.py
natural_time-1.1.5.dist-info/DESCRIPTION.rst
natural_time-1.1.5.dist-info/METADATA
natural_time-1.1.5.dist-info/RECORD
natural_time-1.1.5.dist-info/WHEEL
natural_time-1.1.5.dist-info/metadata.json
natural_time-1.1.5.dist-info/top_level.txt
