Metadata-Version: 2.0
Name: natural-time
Version: 1.1.5
Summary: Tool for understanding dates and times
Home-page: https://github.com/DavidAmison/natural_time
Author: David Amison
Author-email: david.amison20@gmail.com
License: UNKNOWN
Requires-Dist: pathlib
Requires-Dist: python-dateutil
Requires-Dist: textblob
